Metadata-Version: 1.0
Name: pytest-pep8
Version: 1.0.5
Summary: pytest plugin to check PEP8 requirements
Home-page: http://bitbucket.org/hpk42/pytest-pep8/
Author: Holger Krekel and Ronny Pfannschmidt
Author-email: holger.krekel@gmail.com
License: UNKNOWN
Platform: UNKNOWN
